{"source":"Apache Sling's fake-content-generator","section":"Music","folder":"music","filename":"cristopher-medhurst-on-the-bus-of-optical-non-id-aka-rss","title":"Music - Cristopher Medhurst on the bus of optical 'non id' (aka RSS)","tags":["bandwidth"],"seeAlso":["tracy-kling-on-the-sensor-of-mobile-ad-eaque-aka-sms","floy-gislason-on-the-card-of-virtual-quae-veniam-aka-gb","ryder-kemmer-on-the-bandwidth-of-virtual-blanditiis-qui-aka-xml"],"text":"As Cristopher Medhurst often says, Hic voluptatum autem sequi ratione nihil vero. Perspiciatis et porro accusamus fugiat rerum vel ut dicta quisquam. Repellendus est magni earum tempore eius. Vel molestiae ut officiis modi rem. Facilis praesentium accusantium ipsam. Esse cum odit maiores quia sequi explicabo.<br/>\nOmnis dicta aperiam est explicabo quibusdam voluptatem minima. Magnam reprehenderit voluptas accusamus mollitia. Aliquam non ullam in voluptatem occaecati. Pariatur veniam ut qui. Vel totam nemo iste.<br/>\nDistinctio aut aperiam. Ea fuga ratione. Ut natus culpa sit quia quaerat consequatur cumque vitae reiciendis.<br/>\nA sed laborum et. At et dolores sed. Consequatur assumenda quasi cupiditate qui temporibus modi cumque. Officiis voluptatibus magnam doloribus est.<br/>\nNumquam omnis fuga reiciendis quos tempore eos. Est dolor ab consectetur harum numquam nulla. Quasi sed quo aut molestias ut blanditiis perferendis sequi tenetur. Repellat eum architecto consequatur voluptatibus neque dignissimos. Recusandae laborum facere nulla omnis qui necessitatibus at qui sed. Qui eum odit sed inventore.<br/>\nDolorum cum eveniet non voluptatem velit. Eligendi sapiente incidunt amet doloremque. Aspernatur rerum distinctio quibusdam voluptatem molestiae distinctio. Ut ipsa perferendis eum et sunt fuga beatae.<br/>\nMaxime deleniti libero expedita. Qui nihil perferendis voluptatum. Ut quis dolorem. Ipsum blanditiis aliquam.<br/>\nDeserunt eum id. Voluptas aliquid corrupti molestias omnis sit dolores aut animi dicta. Consectetur et nihil in provident corrupti enim laborum ut. Et et non harum repellat nam saepe in ea reiciendis.<br/>\nItaque consequatur repudiandae nemo tempore. Modi veritatis quia recusandae corrupti dicta. Quasi consequatur laboriosam. Et totam consectetur aut iusto ut incidunt voluptatem vel ipsum. Quia aut et pariatur dolore recusandae itaque quia et. Repudiandae earum porro ut dolorem.<br/>\nQuis quis atque quis eos. Aut laboriosam cumque aspernatur sapiente. Nobis deserunt amet voluptatem doloribus ipsam quaerat.<br/>\nAsperiores nihil similique vel explicabo facere voluptas veritatis libero. Inventore dolor animi aut officia quibusdam dolorum doloribus nihil animi. Excepturi corrupti perferendis odio ratione dolor id blanditiis ab. Necessitatibus in et nobis consequatur et voluptates quia. Enim exercitationem molestias non suscipit hic cum molestias doloremque et.","jcr:primaryType":"nt:unstructured","sling:resourceType":"samples/article/music","sling:resourceSuperType":"samples/article"}