{"source":"Apache Sling's fake-content-generator","folder":"business","filename":"cathryn-dickinson-on-the-program-of-multi-byte-fugit-fugiat-aka-xss","title":"Business - Cathryn Dickinson on the program of multi-byte 'fugit fugiat' (aka XSS)","tags":["application","panel"],"seeAlso":["ophelia-weber-on-the-matrix-of-cross-platform-ut-natus-aka-ram","esmeralda-stehr-on-the-bandwidth-of-haptic-vel-exercitationem-aka-com","talia-gleichner-on-the-capacitor-of-multi-byte-quibusdam-iste-aka-ai"],"text":"As Cathryn Dickinson often says, Sit harum at. Voluptatem magni qui vel. Dolores et necessitatibus enim dolorem explicabo. Quibusdam enim et totam et recusandae pariatur omnis. Voluptates odit culpa eos vero in. Natus porro totam sequi aut delectus ullam officia.","jcr:primaryType":"nt:unstructured","sling:resourceType":"samples/article/business","sling:resourceSuperType":"samples/article"}