{"source":"Apache Sling's fake-content-generator","folder":"business","filename":"chesley-farrell-on-the-alarm-of-open-source-velit-labore-aka-adp","title":"Business - Chesley Farrell on the alarm of open-source 'velit labore' (aka ADP)","tags":["application"],"seeAlso":[],"text":"As Chesley Farrell often says, Voluptatem molestiae fugiat necessitatibus repellat totam eius. Voluptatum ut sapiente soluta expedita laboriosam facere id nihil necessitatibus. Veniam laborum delectus. Qui ipsa harum libero ut ut tempore et voluptas.<br/>\nEst ad molestiae voluptas illo reiciendis suscipit. Nobis voluptatum et aut et ullam enim. Illo enim distinctio dolorem et ut et in nulla sunt. Adipisci consequatur enim unde quos nihil. Eum vel autem nostrum enim minus molestias. Minima perspiciatis qui.<br/>\nQui ipsa nesciunt ipsum qui nihil itaque culpa debitis ex. Alias atque a cupiditate cum eum illum totam rerum debitis. Dolore quas est optio quam corrupti molestias tenetur. Dignissimos fugiat culpa vitae fugiat amet incidunt fugit distinctio qui. Qui dolores dolor velit sint eligendi quasi. Aut natus vel vel aut.<br/>\nNisi distinctio distinctio deleniti aut eius. Voluptate autem et quis atque consequatur dolorem. Dolores qui culpa quam molestiae. Qui et quaerat in et eligendi. Odit non nam doloribus suscipit non esse. Quam eos distinctio saepe ad adipisci reiciendis reiciendis.<br/>\nLaboriosam fugiat ipsum sit iusto id quia et velit eaque. Qui aliquid consequatur in exercitationem incidunt soluta cupiditate quibusdam ut. Rerum aliquam aliquid non doloribus illum reprehenderit. Non esse labore enim in laudantium.<br/>\nA ipsum assumenda delectus perferendis. Facere repudiandae voluptas eum. Enim adipisci magni ex sed accusamus quo vero. Omnis non eos quas qui dolores nesciunt veniam.<br/>\nConsequatur quos et occaecati corporis. Voluptas enim facere harum molestias sed veniam. Eius sed iusto tenetur laboriosam. Velit exercitationem adipisci voluptatem. Vel laborum fugiat dolorem blanditiis totam dolor adipisci.<br/>\nCorrupti nisi repellat. Quae nulla non quis voluptas animi recusandae sed sunt voluptatibus. Soluta at voluptas praesentium sint consequuntur et. Numquam qui at ad. Nam unde et occaecati.<br/>\nFugit aut a dolor est omnis. Eos consequatur repellendus aut omnis expedita sed fugiat fuga ut. Quam eum deserunt odio est. Veniam nam tempora est. Et incidunt sint veritatis ipsa vel molestias temporibus ipsa ad. Voluptas nesciunt voluptas veniam suscipit rerum corporis.<br/>\nIpsum dolor similique. Ut tenetur voluptatem dolorum voluptas rerum id. Et exercitationem aperiam eum ab at itaque sapiente.<br/>\nNon saepe voluptas. Non fugiat placeat fugiat. Occaecati non voluptatem. Quos omnis voluptatem deserunt aspernatur. Aut corrupti dolores. Earum aut exercitationem labore ut.<br/>\nSuscipit dolore et laborum in sunt totam tenetur sunt. Dolorem tempore consequatur quod non autem ut soluta. Asperiores nisi neque qui amet soluta aut totam cumque incidunt. In tempore dolorem fugiat et sit neque fugiat.","jcr:primaryType":"nt:unstructured","sling:resourceType":"samples/article/business","sling:resourceSuperType":"samples/article"}