{"source":"Apache Sling's fake-content-generator","folder":"business","filename":"garland-rutherford-on-the-hard-drive-of-primary-sit-et-aka-xss","title":"Business - Garland Rutherford on the hard drive of primary 'sit et' (aka XSS)","tags":["application"],"seeAlso":["garret-deckow-on-the-alarm-of-haptic-officiis-qui-aka-thx","esmeralda-stehr-on-the-bandwidth-of-haptic-vel-exercitationem-aka-com","talia-gleichner-on-the-capacitor-of-multi-byte-quibusdam-iste-aka-ai","novella-balistreri-on-the-transmitter-of-digital-numquam-dolores-aka-adp","deanna-rau-on-the-feed-of-bluetooth-voluptate-fuga-aka-adp"],"text":"As Garland Rutherford often says, Expedita mollitia aut eum dolor fugiat quibusdam nobis sit. Voluptas exercitationem optio commodi dolores et nulla eum. Temporibus illum eum eius et nostrum et. Occaecati quas dicta. Voluptas numquam modi.<br/>\nVoluptatum dolor quia quia et doloribus autem. Esse laborum illum rerum vel nulla et dignissimos. Distinctio doloremque aliquam nulla facere impedit et ipsa consectetur.<br/>\nSaepe distinctio velit. Nisi quia ea. Rerum vero exercitationem ut qui natus pariatur atque ea. Qui veritatis enim quis et illum sint et sint. Nisi debitis accusantium dignissimos nostrum totam soluta.<br/>\nSunt ducimus est dolorem assumenda dignissimos repellendus nam officiis. Eum est quas beatae. Inventore aspernatur vel et blanditiis exercitationem dolorem nemo officia.<br/>\nSit nihil vero qui et labore hic voluptate veritatis. Consectetur itaque modi aliquam ut. Assumenda hic quidem quo id eum consequatur.<br/>\nVoluptatem molestiae cumque reiciendis facere sit. Sed expedita incidunt sint porro cumque dolorum eum vero. Ipsum tenetur tenetur debitis ea quos voluptatem ipsam dolorem rem. Labore ipsa nihil cum dolor aut consequatur ut voluptatem magnam. Qui aliquid consectetur eum eligendi. Ut dicta est recusandae non.<br/>\nQuos error sit id. Ut dignissimos et maiores sint aut illum aperiam eveniet. Et laboriosam aut placeat velit dolor alias omnis ut. Totam quaerat sunt est et consequatur ullam voluptatibus nobis. Aut eveniet cupiditate incidunt et et ab ut.<br/>\nConsectetur in rerum earum officiis qui. Aut est fugit voluptatem. Sed quibusdam pariatur incidunt amet ab minus eius. Qui est eos ducimus consectetur similique saepe qui aspernatur aliquam. Pariatur iure quia.<br/>\nOdio ut commodi quibusdam pariatur quas nihil inventore maiores quam. Sint molestias aut. Officia et autem incidunt dolore sapiente quibusdam sit. Quod adipisci odio non ullam. Vel earum deserunt tempore veniam rem rerum sit. Eius voluptates repellat voluptatem consequuntur odit veritatis commodi ad.<br/>\nTenetur debitis optio et facere qui est. Ullam corporis laborum dolores ut. Unde nisi accusantium tempora ex veritatis. Aut cum velit amet qui quidem sed.<br/>\nSed doloribus nihil est deserunt. Odit accusamus nulla. Velit ex provident odit est quidem amet earum. Voluptatem aut quaerat fugit. At voluptatem voluptas veritatis assumenda consequuntur et distinctio est delectus. Iste et nesciunt neque suscipit voluptate fugiat qui consequatur ipsam.","jcr:primaryType":"nt:unstructured","sling:resourceType":"samples/article/business","sling:resourceSuperType":"samples/article"}