{"source":"Apache Sling's fake-content-generator","folder":"business","filename":"jarret-ankunding-on-the-pixel-of-back-end-accusantium-tempore-aka-json","title":"Business - Jarret Ankunding on the pixel of back-end 'accusantium tempore' (aka JSON)","tags":["card","application"],"seeAlso":[],"text":"As Jarret Ankunding often says, Est sunt sunt cumque. Omnis laborum ut quod qui enim inventore et et sed. Suscipit nemo officiis.<br/>\nFacere cupiditate eos quod mollitia et atque debitis. Corporis voluptate repellendus deleniti doloremque. Ab consequuntur voluptatem expedita deleniti facilis veritatis facere qui praesentium. Veniam aut ratione optio quisquam ipsum omnis. Quasi incidunt vitae cupiditate. Aperiam nemo quaerat.<br/>\nSaepe unde at consectetur aspernatur. Eius molestiae aliquam id illum voluptates labore et autem optio. Et magni tempora ullam est quos aliquam expedita officiis sit. Aut voluptatem in qui.<br/>\nDolorum facilis officiis eveniet repudiandae explicabo maiores. Magnam voluptate tempora architecto. Non rem quas aperiam quo voluptas quod sint nihil. Delectus ut omnis enim quod voluptatem ad aut corrupti similique.<br/>\nEst qui praesentium modi. Quia quas iste consequatur unde ut praesentium. Quis tenetur velit officiis voluptate et nobis et et consectetur. Incidunt laboriosam consequatur. Beatae consequatur magnam aut dolor aut pariatur harum. Iste iusto dignissimos.<br/>\nNulla voluptas itaque voluptatem qui aut. Dignissimos est eos et ut dicta eaque distinctio. Laboriosam et occaecati cumque minus commodi sint et beatae rerum. Eum vel fugit nemo quia. Sunt libero qui culpa. Consequatur non eos aliquam inventore in aliquid sed non.<br/>\nLibero cum rerum placeat quia corporis qui quia voluptatem et. Adipisci enim et quas facilis est optio. Voluptatem dolore eum laborum est.<br/>\nEt cum iusto animi cupiditate nam ea odio sed ratione. Dolores veritatis expedita quia inventore ducimus. Tenetur omnis sapiente saepe autem et ullam repudiandae aut. Est pariatur in explicabo repellendus ea dolorem. Provident sed harum esse et ut aut sint placeat. Autem rerum quidem quis dolorum.<br/>\nEnim repellat quis nesciunt. Molestiae assumenda sed aperiam qui fugit repellendus minus exercitationem. Facilis sit distinctio sit velit repudiandae laudantium velit corporis. Quisquam occaecati nesciunt sint officiis quis.","jcr:primaryType":"nt:unstructured","sling:resourceType":"samples/article/business","sling:resourceSuperType":"samples/article"}