{"source":"Apache Sling's fake-content-generator","folder":"business","filename":"jarret-considine-on-the-alarm-of-virtual-adipisci-blanditiis-aka-agp","title":"Business - Jarret Considine on the alarm of virtual 'adipisci blanditiis' (aka AGP)","tags":["application","alarm","sensor"],"seeAlso":["garret-deckow-on-the-alarm-of-haptic-officiis-qui-aka-thx"],"text":"As Jarret Considine often says, Consequatur quia facilis doloribus earum impedit laudantium ipsa. Magni architecto ut doloribus et. Dolorem assumenda a est.<br/>\nIpsam hic quas recusandae numquam nostrum perspiciatis. Fuga exercitationem eligendi sed. Et non maxime corrupti ut. Voluptates maxime molestias distinctio similique ducimus autem molestias.<br/>\nIllum quia voluptas repellendus reprehenderit. Reprehenderit culpa quis quo sed dolorem nulla qui. Eligendi est rem reiciendis eligendi vero quasi dignissimos.<br/>\nEt quidem reprehenderit veniam laudantium similique est ipsum. Reprehenderit consectetur voluptatibus dolorum veritatis vel autem nemo id eum. Quo quis cupiditate enim omnis autem animi.<br/>\nHarum facere rerum exercitationem nesciunt perspiciatis esse nemo. Nam debitis dolorem quod eum. Qui quia consequatur sed.<br/>\nIllum voluptas commodi. Cumque ut aliquam rerum a voluptatem rerum repellat consequatur. Occaecati ab eligendi quia nemo ut omnis possimus doloremque. Non nesciunt consequatur ducimus excepturi unde voluptas quibusdam. Facere neque quaerat velit impedit.","jcr:primaryType":"nt:unstructured","sling:resourceType":"samples/article/business","sling:resourceSuperType":"samples/article"}