{"source":"Apache Sling's fake-content-generator","section":"News","folder":"news","filename":"cara-reichert-on-the-bus-of-online-aut-inventore-aka-json","title":"News - Cara Reichert on the bus of online 'aut inventore' (aka JSON)","tags":["protocol","array"],"seeAlso":["belle-jacobi-on-the-feed-of-online-vel-aut-aka-ai","floy-gislason-on-the-card-of-virtual-quae-veniam-aka-gb"],"text":"As Cara Reichert often says, ","jcr:primaryType":"nt:unstructured","sling:resourceType":"samples/article/news","sling:resourceSuperType":"samples/article"}