{"source":"Apache Sling's fake-content-generator","section":"Adventure","folder":"adventure","filename":"dax-champlin-on-the-card-of-back-end-blanditiis-eum-aka-smtp","title":"Adventure - Dax Champlin on the card of back-end 'blanditiis eum' (aka SMTP)","tags":["monitor","array","driver"],"seeAlso":["solon-davis-on-the-card-of-primary-reiciendis-omnis-aka-sql"],"text":"As Dax Champlin often says, Enim in impedit veritatis dolores ut. Vitae alias dicta tempore est odit nemo voluptas autem molestiae. Distinctio ut facere rerum consequatur hic. Inventore fuga aut ab omnis aut. Molestiae doloribus incidunt inventore sit sunt. Ut animi dolorem delectus molestiae voluptatem quo quibusdam deleniti.<br/>\nCulpa qui ut qui hic. Dolorem dolore possimus provident animi eum distinctio sunt laudantium. Earum perferendis in quia voluptatum vitae reiciendis perferendis. Blanditiis culpa provident cumque mollitia veniam accusantium vel enim. Ut mollitia asperiores.","jcr:primaryType":"nt:unstructured","sling:resourceType":"samples/article/adventure","sling:resourceSuperType":"samples/article"}