{"source":"Apache Sling's fake-content-generator","section":"Adventure","folder":"adventure","filename":"monserrate-stanton-on-the-sensor-of-1080p-animi-est-aka-exe","title":"Adventure - Monserrate Stanton on the sensor of 1080p 'animi est' (aka EXE)","tags":["monitor","protocol","array"],"seeAlso":["solon-davis-on-the-card-of-primary-reiciendis-omnis-aka-sql","fermin-bernhard-on-the-capacitor-of-mobile-rerum-aliquid-aka-adp"],"text":"As Monserrate Stanton often says, Blanditiis explicabo id quam enim cum voluptatem. Dicta reiciendis aliquid similique dignissimos similique et a incidunt quisquam. Optio dignissimos nisi. Voluptas et velit autem adipisci.<br/>\nPerferendis atque iure velit dolorum nobis. Ullam tempora eaque alias cupiditate. Voluptates sint suscipit vel sit adipisci. Aut ullam quia error officia sunt minus perspiciatis ratione. Veniam nulla expedita fuga voluptas laboriosam expedita vero laborum fugit. Et nihil ipsa temporibus.<br/>\nEos qui dolore ipsa totam voluptas quaerat quod. Illo est et maxime quasi deserunt nesciunt qui rerum consequuntur. Voluptas dolor nostrum et vel.","jcr:primaryType":"nt:unstructured","sling:resourceType":"samples/article/adventure","sling:resourceSuperType":"samples/article"}