{"source":"Apache Sling's fake-content-generator","section":"Adventure","folder":"adventure","filename":"vernice-waters-on-the-panel-of-wireless-odio-est-aka-xml","title":"Adventure - Vernice Waters on the panel of wireless 'odio est' (aka XML)","tags":["bandwidth","monitor"],"seeAlso":["solon-davis-on-the-card-of-primary-reiciendis-omnis-aka-sql","tracy-kling-on-the-sensor-of-mobile-ad-eaque-aka-sms","floy-gislason-on-the-card-of-virtual-quae-veniam-aka-gb"],"text":"As Vernice Waters often says, Quia aspernatur veritatis. Et deleniti quis sequi et omnis voluptas eos in. Nulla beatae quos inventore est iure sint. Accusantium aspernatur quo vel est aspernatur illo consequatur qui. Repellendus omnis nisi. Consectetur aut aut ipsam omnis nihil sit.<br/>\nDignissimos nemo qui ut minima. Exercitationem aperiam est asperiores veritatis. Quod vitae itaque ut blanditiis. Debitis voluptatibus blanditiis facere in tenetur nostrum placeat et perferendis.<br/>\nDolor eum tenetur qui laborum cupiditate hic qui ducimus amet. Voluptatem molestiae maiores ut harum id voluptas aperiam at. Hic corrupti voluptas facere occaecati quod officiis. Distinctio qui recusandae ut sunt est aut. Atque et voluptatibus et fugit maiores quibusdam et veritatis.<br/>\nEst similique dolorem sequi illum quam odio. Aut eum odio non pariatur voluptates molestias voluptatem soluta amet. Fugiat repellat molestias quis architecto est voluptas. Similique sunt qui voluptatem. Qui autem et illum. Qui error harum aliquid rerum mollitia.<br/>\nAutem velit consequatur voluptatem dolorum ut aut nemo ut veniam. Saepe similique sed. Rerum vel iste et reprehenderit et et consequatur.<br/>\nRem dicta molestias voluptatem. Repellendus numquam porro animi voluptatem omnis voluptatem. Rerum quasi aut ut. Consequatur sapiente sint voluptate. Sunt dolore molestiae esse dolorem voluptatum corporis quo tempore.<br/>\nAliquid est fugit velit vel reprehenderit veritatis accusamus provident. Minus voluptas odio repellat tenetur. Voluptas deserunt corporis incidunt enim. Et et aut dignissimos voluptas quia.<br/>\nVelit qui dolores sit dolorum ipsam rerum est id blanditiis. Autem et optio sunt reprehenderit labore ut qui. Sed atque dolores.<br/>\nDolores temporibus repudiandae a quidem velit consectetur expedita quia. Dignissimos dolor odio ab aut eos molestias quis itaque. Beatae est nisi nostrum. Placeat eligendi soluta. Facilis explicabo et voluptates.<br/>\nItaque quis ex ducimus aut odit qui sunt aut adipisci. Quis numquam voluptate ipsum et praesentium amet. Sint et laboriosam odit quam sit sit aut enim.<br/>\nNisi id velit sed cum illo sunt. Non earum blanditiis eius hic. Est doloribus eos rerum quasi. Doloremque et nihil illo corrupti accusantium consectetur maxime.<br/>\nIpsam aut facilis eos dolore enim enim placeat nemo tempore. Officia id eveniet enim veniam laborum. Ut debitis in. Quam veniam sunt sed cumque quibusdam qui. Eius a laboriosam.","jcr:primaryType":"nt:unstructured","sling:resourceType":"samples/article/adventure","sling:resourceSuperType":"samples/article"}