{"source":"Apache Sling's fake-content-generator","section":"Adventure","folder":"adventure","filename":"barrett-upton-on-the-system-of-cross-platform-amet-error-aka-sms","title":"Adventure - Barrett Upton on the system of cross-platform 'amet error' (aka SMS)","tags":["bandwidth"],"seeAlso":["solon-davis-on-the-card-of-primary-reiciendis-omnis-aka-sql"],"text":"As Barrett Upton often says, Suscipit et esse et dolores. Aut porro velit totam minima voluptas quo. Aut distinctio quia fugiat natus ut et quam omnis molestiae. Quia adipisci adipisci nam nulla et. Veritatis velit qui sint ipsa iste corporis omnis.<br/>\nItaque eum qui in ducimus sapiente asperiores. Accusamus pariatur doloribus consequatur dolorem. Tempore ab asperiores et ducimus non quasi ratione quidem. Debitis vero magni.<br/>\nBeatae est ab excepturi sit natus nobis. Aliquam quam ut. Perferendis est pariatur nulla totam eos. Aut impedit numquam doloremque qui totam praesentium consequatur eaque. Rem dolorum cupiditate impedit molestias nam et ea qui quaerat. Minima explicabo molestiae aut nam cum deserunt fugit.<br/>\nAmet similique minus voluptatem ipsam aut est occaecati odit. Vitae est possimus vero et non. Inventore placeat eos consequatur minus molestiae velit tenetur.<br/>\nAliquam sequi quas unde aspernatur vel. Magnam quia officiis. Modi dolorum earum ad vel nemo non cum blanditiis. Consequuntur inventore dolor illo a perspiciatis. Qui reiciendis totam saepe omnis odio consequatur fugiat. Rem omnis quis et ullam eveniet.<br/>\nRepellat qui ratione possimus repudiandae est in. Tempora voluptatem ut optio temporibus et. Quod aperiam et qui. Et et ut. Qui id molestiae beatae doloremque eos. Ab eligendi quasi.<br/>\nVelit rerum aut est sit sit culpa nisi explicabo tenetur. Repellat mollitia quidem. Aut et maiores maiores veritatis omnis odio omnis laborum minus. Quas voluptate quis et velit vitae et.<br/>\nOmnis recusandae ut consequatur sint. Ullam id magni architecto architecto voluptatem ut aut dolores qui. Et eum magnam et doloremque. Quibusdam et ex. Voluptas non exercitationem consequatur quo ab autem commodi alias asperiores. Dignissimos placeat nihil molestias quaerat velit et.<br/>\nUt eligendi quaerat rerum reiciendis est. Rem adipisci aut accusamus est dolorem culpa aliquid. Vitae vel quia dolore voluptas modi. Dolor culpa quo consequuntur autem accusamus. Fugiat et accusantium repellat autem eum vero quae. Asperiores repellendus dolorem molestiae eos maxime animi consequatur sint adipisci.","jcr:primaryType":"nt:unstructured","sling:resourceType":"samples/article/adventure","sling:resourceSuperType":"samples/article"}