{"source":"Apache Sling's fake-content-generator","folder":"adventure","filename":"ernest-cremin-on-the-application-of-haptic-asperiores-aut-aka-xml","title":"Adventure - Ernest Cremin on the application of haptic 'asperiores aut' (aka XML)","tags":["card","application","firewall","sensor"],"seeAlso":["garret-deckow-on-the-alarm-of-haptic-officiis-qui-aka-thx"],"text":"As Ernest Cremin often says, Et quaerat dolor ratione temporibus nisi non. Veritatis commodi asperiores est praesentium corporis itaque. Et qui dolor veritatis illo consequatur.<br/>\nEt aut asperiores tempore in temporibus voluptatem minima. Est voluptates voluptatem ipsum vero ea. Mollitia voluptatem exercitationem suscipit tenetur maxime maxime. Voluptatum voluptas id quibusdam sunt qui blanditiis doloribus delectus hic. Voluptates assumenda soluta illum nostrum illum. Inventore officia qui quidem modi consequatur et non porro.<br/>\nAd molestiae quis qui adipisci repudiandae deserunt atque. Veritatis ut sint. Nulla saepe pariatur rem quis eum provident quos unde maxime. Molestiae quis aut.","jcr:primaryType":"nt:unstructured","sling:resourceType":"samples/article/adventure","sling:resourceSuperType":"samples/article"}