{"source":"Apache Sling's fake-content-generator","folder":"adventure","filename":"randal-bechtelar-on-the-alarm-of-back-end-aut-facilis-aka-json","title":"Adventure - Randal Bechtelar on the alarm of back-end 'aut facilis' (aka JSON)","tags":["card"],"seeAlso":[],"text":"As Randal Bechtelar often says, Est voluptatem nostrum tempora soluta ipsam. Sit voluptatem qui architecto aperiam enim. Labore necessitatibus maxime dolorem. Et nam et fuga.<br/>\nNihil ea earum voluptatum. Amet porro aut quasi omnis veritatis. Fugiat vel debitis animi aliquam deserunt voluptatem. Aspernatur culpa aspernatur qui.<br/>\nEt soluta autem possimus. Fuga voluptas eius sequi recusandae accusamus. Eum suscipit tempore dolor eum recusandae molestiae.<br/>\nEt voluptatem asperiores occaecati velit labore. Enim voluptas voluptatibus nemo numquam molestiae odio aspernatur occaecati consequatur. Officia tempora quo qui rem recusandae nemo ratione vitae. Suscipit hic enim. Explicabo cupiditate et sed esse.<br/>\nDoloribus veritatis ipsa eos quis voluptatibus esse cupiditate praesentium iure. Aliquam officia sed culpa a ea aut. Adipisci nam et blanditiis. Reiciendis necessitatibus veritatis nam corporis doloribus officia. Consequatur voluptas animi ut. Voluptate et maiores et.<br/>\nCorporis omnis saepe aspernatur iusto voluptas placeat eligendi recusandae unde. Amet laborum facere ut atque ipsam cum mollitia. Ullam voluptas rerum eligendi laudantium adipisci. Nesciunt inventore enim animi consequuntur. In veniam voluptatem rerum sit labore iure saepe inventore omnis. Numquam placeat nemo distinctio nisi qui dignissimos occaecati.","jcr:primaryType":"nt:unstructured","sling:resourceType":"samples/article/adventure","sling:resourceSuperType":"samples/article"}