{"source":"Apache Sling's fake-content-generator","section":"Culture","folder":"culture","filename":"lea-kshlerin-on-the-panel-of-multi-byte-qui-quod-aka-xss","title":"Culture - Lea Kshlerin on the panel of multi-byte 'qui quod' (aka XSS)","tags":["bandwidth"],"seeAlso":["floy-gislason-on-the-card-of-virtual-quae-veniam-aka-gb"],"text":"As Lea Kshlerin often says, Impedit libero fugit. Vitae mollitia minima eveniet omnis quisquam fugiat odit non. Qui est voluptates tempore labore quia non tenetur laudantium et.<br/>\nQui neque aut voluptate dolorem repudiandae et consequuntur. Molestiae cumque et dicta. Saepe veritatis aut.<br/>\nEa maxime autem ipsum quisquam. Aut vero repellendus. Praesentium velit voluptates nihil labore voluptatem. Voluptas sit aut eum modi temporibus sunt. Dolorem maiores omnis nisi et ut. Quibusdam delectus qui non eaque culpa quia optio.<br/>\nQuis dolores unde tenetur incidunt veniam corrupti ut. Dolorem facilis aspernatur qui et aliquam. Dolores culpa fugiat. Id beatae est labore at. Veniam autem rerum voluptatem qui corporis velit.<br/>\nQuia et unde tenetur totam. Nihil nisi doloremque molestiae consequatur ea. Sed distinctio omnis reprehenderit molestiae exercitationem vitae similique.<br/>\nLibero animi aut quam reprehenderit itaque quis perspiciatis. Ad explicabo quas dolor eos omnis consequatur ab. Incidunt ratione dolor in non est. Corrupti quaerat aut quo quia tenetur rem ipsam.<br/>\nNeque non ea expedita enim maxime est. Sed voluptatibus ad aliquid porro sit vel cumque et. Quod officia voluptatem quaerat doloremque consequuntur provident temporibus similique. Optio est nemo. Velit enim molestiae.","jcr:primaryType":"nt:unstructured","sling:resourceType":"samples/article/culture","sling:resourceSuperType":"samples/article"}