{"source":"Apache Sling's fake-content-generator","folder":"culture","filename":"bradly-botsford-on-the-card-of-online-ut-id-aka-ai","title":"Culture - Bradly Botsford on the card of online 'ut id' (aka AI)","tags":["card"],"seeAlso":["ophelia-weber-on-the-matrix-of-cross-platform-ut-natus-aka-ram"],"text":"As Bradly Botsford often says, Aperiam ut est quas doloremque est quia alias delectus. Saepe corrupti qui quasi incidunt sequi. Et esse voluptatem atque.<br/>\nAliquam dolores maiores dicta molestiae qui aperiam molestiae sed corrupti. Nemo delectus reiciendis dolorem ea eos soluta voluptas. Ut qui ea sapiente dolorem quaerat voluptatem reiciendis. Expedita veritatis minus similique quam animi. Minima aut voluptatem.<br/>\nAdipisci tempore consequatur ipsam laborum nulla. Dolore repudiandae enim quia dolor officiis qui. In aut doloribus vel aliquam cum alias et et.<br/>\nEveniet voluptas labore. Reprehenderit veritatis iusto voluptatum voluptatem magnam hic molestiae incidunt. Distinctio omnis placeat omnis repellat. Recusandae aut eum. Fugiat optio pariatur sit optio aperiam quod. Voluptatem assumenda repudiandae animi placeat vel laboriosam et aliquid.<br/>\nEt debitis aut dolor aut. Voluptas deserunt est quo fuga tempora sint quis. Id ratione ea saepe voluptas tempora repudiandae neque similique quasi. Voluptatem rerum perferendis ea quisquam itaque. Ut cum deleniti itaque. Tempora officiis delectus voluptas dolor.<br/>\nMaiores itaque consequuntur. Natus atque tenetur soluta fugiat voluptate. Dicta ipsam rerum est. Dignissimos quia ea.","jcr:primaryType":"nt:unstructured","sling:resourceType":"samples/article/culture","sling:resourceSuperType":"samples/article"}