{"source":"Apache Sling's fake-content-generator","folder":"music","filename":"roy-heaney-on-the-card-of-primary-voluptatum-impedit-aka-thx","title":"Music - Roy Heaney on the card of primary 'voluptatum impedit' (aka THX)","tags":[],"seeAlso":["garret-deckow-on-the-alarm-of-haptic-officiis-qui-aka-thx","talia-gleichner-on-the-capacitor-of-multi-byte-quibusdam-iste-aka-ai"],"text":"As Roy Heaney often says, Labore atque dolores. Ut natus excepturi fuga debitis sequi aut explicabo vero. Ea quis vitae aut numquam exercitationem molestiae suscipit. Ut quod laboriosam laudantium quae eos. Animi provident repudiandae non aut non quia ipsa a recusandae.<br/>\nProvident perferendis perspiciatis voluptatem eaque similique aliquam aperiam qui qui. Iste modi sed enim perspiciatis tenetur deleniti consequatur facere. Qui nihil delectus nobis quidem eum ut.<br/>\nQui qui voluptatem quaerat voluptate et sequi et. Quae eveniet dolor aut nam impedit. Non doloribus doloremque a numquam sed totam labore.<br/>\nAb aliquam est quo quia sit ipsa. Et est distinctio corrupti ex qui laudantium ad. Voluptas ea saepe quisquam mollitia sed. Non doloribus consectetur neque.<br/>\nTempora beatae sunt ex qui cum aspernatur expedita modi. Aut quia numquam quidem sed facilis. Deserunt nihil fugiat aliquam tenetur ex. Vero quis non non dolore ducimus sit. Atque corporis explicabo est. Vel sunt natus sunt qui totam.<br/>\nDolore delectus aut non. Cum libero cum excepturi facilis ea officiis. Qui cupiditate ea et quia velit reiciendis repudiandae sed.<br/>\nQuibusdam enim voluptatem mollitia voluptatibus maxime aut quos quod fugiat. Mollitia eaque possimus facere. Accusamus eius consequatur quod aut blanditiis.<br/>\nAut ab et. Ut ex blanditiis magnam saepe iure quis et fugiat. Nesciunt omnis dolore est reiciendis sed voluptatem sequi voluptate. Voluptatem nihil eveniet dolores inventore totam.<br/>\nDignissimos voluptatem nostrum illo exercitationem occaecati occaecati. Nam reprehenderit esse quos quaerat perspiciatis sint. Id est sit quo veniam quos. Magni in id et. Porro veritatis aliquam unde ratione ab.","jcr:primaryType":"nt:unstructured","sling:resourceType":"samples/article/music","sling:resourceSuperType":"samples/article"}