{"source":"Apache Sling's fake-content-generator","folder":"travel","filename":"dasia-mclaughlin-on-the-capacitor-of-solid-state-dolor-qui-aka-jbod","title":"Travel - Dasia McLaughlin on the capacitor of solid state 'dolor qui' (aka JBOD)","tags":["card","sensor"],"seeAlso":["ophelia-weber-on-the-matrix-of-cross-platform-ut-natus-aka-ram"],"text":"As Dasia McLaughlin often says, Ex ipsam nobis quo est ipsa. Labore voluptas ea vel sapiente qui. Est corrupti itaque autem ipsam. Deserunt reiciendis commodi magni corporis. Quis qui corrupti quia aut.<br/>\nEst dolore voluptas totam. Nemo perspiciatis ut suscipit. Dignissimos aliquid qui repellat vel earum adipisci porro. Occaecati vero ut est dolorum corporis ipsum quo repudiandae non.<br/>\nOfficia quas officiis exercitationem sapiente expedita. Error in et qui molestias quod id. Explicabo iusto a quaerat dolores quas. Nisi placeat inventore exercitationem. Placeat velit enim libero.<br/>\nVero illo eius amet ea enim sequi quis corrupti est. Earum sapiente incidunt iure nulla. Aspernatur repellendus modi fugit saepe tenetur eius id.<br/>\nConsequatur nihil eos nulla. Neque asperiores dicta commodi adipisci quos. In et est. Aliquam laudantium architecto perspiciatis mollitia non fuga voluptatem aut.","jcr:primaryType":"nt:unstructured","sling:resourceType":"samples/article/travel","sling:resourceSuperType":"samples/article"}