{"source":"Apache Sling's fake-content-generator","folder":"travel","filename":"julia-batz-on-the-pixel-of-digital-minima-maiores-aka-css","title":"Travel - Julia Batz on the pixel of digital 'minima maiores' (aka CSS)","tags":["card"],"seeAlso":["garret-deckow-on-the-alarm-of-haptic-officiis-qui-aka-thx"],"text":"As Julia Batz often says, Beatae sed sint aut. Est sit dicta ut possimus quia ut libero numquam praesentium. Necessitatibus in aut. Magnam quae suscipit consequatur quisquam asperiores.","jcr:primaryType":"nt:unstructured","sling:resourceType":"samples/article/travel","sling:resourceSuperType":"samples/article"}