{"source":"Apache Sling's fake-content-generator","folder":"travel","filename":"verla-roberts-on-the-panel-of-primary-accusantium-et-aka-rss","title":"Travel - Verla Roberts on the panel of primary 'accusantium et' (aka RSS)","tags":["card","application"],"seeAlso":["garret-deckow-on-the-alarm-of-haptic-officiis-qui-aka-thx"],"text":"As Verla Roberts often says, Repellendus provident et quisquam inventore sit nulla explicabo. Nostrum est dignissimos aut enim minima corporis. Labore aliquam alias et quis ea qui ducimus nesciunt animi. Quos qui laboriosam earum ut sed modi ut culpa autem.<br/>\nSaepe aut quam dolores. Quia qui accusantium consectetur repudiandae exercitationem. Nisi eius minus sit officiis nisi molestias nemo accusantium omnis. Cum et error. Repudiandae cupiditate laborum ut.<br/>\nQuia at vel fuga iure. Quia aperiam reprehenderit dolor et vel voluptas at eius. Quia et quia unde soluta facere hic ea. Officia a exercitationem sit atque sed non pariatur.<br/>\nSit ipsa quae quia omnis praesentium suscipit soluta. Est eligendi eos deleniti aut. Veritatis corporis earum facilis eaque voluptas et sed sapiente nemo. Molestiae fugiat minus.","jcr:primaryType":"nt:unstructured","sling:resourceType":"samples/article/travel","sling:resourceSuperType":"samples/article"}