{"source":"Apache Sling's fake-content-generator","folder":"news","filename":"erling-johnston-on-the-panel-of-neural-fugit-quas-aka-hdd","title":"News - Erling Johnston on the panel of neural 'fugit quas' (aka HDD)","tags":["panel"],"seeAlso":["garret-deckow-on-the-alarm-of-haptic-officiis-qui-aka-thx"],"text":"As Erling Johnston often says, Facilis dicta sed. Beatae nam voluptatem nihil illum explicabo. Quo et labore impedit impedit velit. Molestiae minima ab et. Nobis provident aut eos id maiores sunt sit illo voluptas.<br/>\nAnimi minima ea. Et esse esse omnis aspernatur alias sit iste sequi maiores. Eligendi et optio vero est nihil sed voluptas. Aut facere sint. Assumenda ut autem aut ex odio dolore est. Amet voluptatem quod sapiente tempore eius magnam nesciunt.<br/>\nPlaceat doloremque aliquid. Quidem consectetur et magni. Ut atque doloribus. Dolor velit nihil sed cum laborum. Delectus quod tenetur numquam sunt. A saepe soluta debitis doloribus atque.<br/>\nNihil eaque rerum consequatur ex debitis hic facilis est quia. Beatae reprehenderit consequatur quia tempora autem eos et recusandae. Adipisci aut voluptatum ut. Fugiat hic et tenetur itaque aliquam repudiandae sint cupiditate odio. Officia pariatur enim animi doloremque officia voluptates et. Tenetur recusandae labore veniam earum temporibus quae.<br/>\nAb at aliquam ut incidunt voluptatem. Ab porro vitae autem ab quaerat. Assumenda illum quo blanditiis amet iure rem ullam labore. Tenetur voluptatem repudiandae. Culpa voluptatibus accusamus ratione architecto eos. A culpa porro voluptas.<br/>\nEaque minus maiores qui ut ipsam. Architecto incidunt repellendus. Qui quibusdam ratione. Qui architecto praesentium fugit et nihil odit.<br/>\nSed consequatur architecto voluptas quisquam sequi ipsum cupiditate consequatur odio. Libero et et non illo ea nam porro. Consequatur quibusdam et assumenda deleniti molestias voluptatem maiores quo consequatur. Sapiente veniam aliquid debitis beatae.<br/>\nEveniet fugiat aut nulla reiciendis voluptate. Vitae quibusdam aliquam distinctio quis et voluptas eligendi velit. Accusantium deleniti eos qui optio consequatur debitis repellendus adipisci. Ipsum voluptatibus repellendus aut repudiandae veniam nesciunt. Mollitia nostrum explicabo et error consequatur. Laudantium omnis quibusdam repellat praesentium.<br/>\nQuis ratione eum est voluptas ipsum. Ut sit quo aperiam. Saepe veritatis ut neque debitis quasi sed qui. Nostrum impedit nesciunt qui qui distinctio est. Ut hic non consequatur dolorem molestiae dolores.<br/>\nDolorem repellat quisquam sed. At atque numquam soluta non blanditiis quia sit. Quo dolores impedit illum ut architecto ut.<br/>\nEa omnis dicta. Minus eius veniam modi consequatur quis maiores tenetur autem et. Non nulla ratione vel dolorem sed modi. Aut ut et esse nemo qui.<br/>\nEt corrupti et molestiae eum cupiditate. Ea minima dolores illo commodi est. Dolorem atque est id qui asperiores quisquam. Sit debitis enim quae excepturi hic nulla non. Eligendi aspernatur aperiam ea qui sed consequuntur.","jcr:primaryType":"nt:unstructured","sling:resourceType":"samples/article/news","sling:resourceSuperType":"samples/article"}