{"source":"Apache Sling's fake-content-generator","section":"News","folder":"news","filename":"amara-pacocha-on-the-circuit-of-optical-nostrum-facere-aka-smtp","title":"News - Amara Pacocha on the circuit of optical 'nostrum facere' (aka SMTP)","tags":[],"seeAlso":["belle-jacobi-on-the-feed-of-online-vel-aut-aka-ai"],"text":"As Amara Pacocha often says, Aliquam beatae quaerat sit in quo illum officia. Reiciendis commodi sed iste occaecati omnis. Et quis totam saepe sit aspernatur veniam.<br/>\nEt distinctio qui minus. Quasi voluptatem qui tempore et aut qui. Possimus voluptas doloribus error illum voluptatem velit aut eveniet omnis. Et libero nisi et sint optio sint vero.<br/>\nNam consequuntur veniam neque et. Nesciunt quia veritatis mollitia eveniet sint mollitia cum a vitae. Qui officiis voluptas alias quia totam occaecati aut. Placeat rerum ad incidunt.<br/>\nIusto repellat commodi nostrum nostrum et. Ea incidunt aut. Quis soluta sed nesciunt aut est. Quasi facere autem facere aliquid. Ut sit rerum placeat ut aut quis quam incidunt vel. Error placeat id labore consequuntur sit perferendis explicabo quod rem.<br/>\nEt quia eos autem et. Omnis tempore voluptate ut ipsam dignissimos. Voluptatum quia iste et qui ut voluptatem. Beatae quos est animi. Non sed cum.<br/>\nAliquid odit veritatis occaecati. Maxime quia ut. Quam voluptas quisquam et. Et et maxime necessitatibus nesciunt magnam in temporibus. Ratione dignissimos voluptas et alias non quam. Officiis et aut atque cum eveniet corporis.<br/>\nEst deserunt odio repudiandae omnis sed dolor ut voluptatibus nulla. Enim repudiandae qui neque consequatur aspernatur sit nesciunt id. Unde libero eius.<br/>\nId repellendus enim vitae sunt sint vel. Esse dolor fuga et. Iusto consequatur qui qui rem quo maiores. Sed perferendis ut non qui quis hic.<br/>\nA blanditiis quibusdam et et. Labore rerum doloribus provident ea eius enim. Perspiciatis earum ratione quisquam. Animi hic accusantium laudantium porro soluta placeat repudiandae. Esse iste facere est. Quidem eos ut.<br/>\nMolestias est reprehenderit est. Soluta nesciunt dolore modi fuga asperiores et sequi eum vel. Illum est ut nihil repellendus velit praesentium praesentium unde. Deleniti non enim laboriosam earum illum. Praesentium hic nisi sed ipsa suscipit qui illo. Qui et fugit maiores asperiores et libero rem impedit quia.<br/>\nEst velit vel et impedit quia iusto mollitia illum placeat. Dolores blanditiis voluptatem error est aut veritatis qui. Sed qui ipsam est dolores veritatis tempora quae praesentium. At et quia blanditiis.","jcr:primaryType":"nt:unstructured","sling:resourceType":"samples/article/news","sling:resourceSuperType":"samples/article"}