{"source":"Apache Sling's fake-content-generator","section":"News","folder":"news","filename":"colten-schumm-on-the-circuit-of-online-reprehenderit-ut-aka-adp","title":"News - Colten Schumm on the circuit of online 'reprehenderit ut' (aka ADP)","tags":[],"seeAlso":[],"text":"As Colten Schumm often says, At accusantium soluta accusamus qui cumque. Sit incidunt et odio repudiandae tenetur odio. Repellendus quis deserunt consequatur hic illo. Possimus aspernatur voluptatum error dolorem voluptatibus cumque.<br/>\nQui consequuntur ipsum ut ipsam in velit. Libero omnis fuga voluptate eos. Praesentium architecto mollitia. Sed dolore commodi. Aut et expedita fuga dignissimos voluptates. Et ipsa deleniti et eum et error.<br/>\nQuo qui reiciendis. Odit qui molestias totam non id nobis a corporis. Modi tempore inventore deleniti amet possimus pariatur excepturi deserunt. Cum officia laboriosam velit molestiae velit. Enim rerum eveniet cupiditate odit.<br/>\nIllo aut aut labore sint eaque temporibus aut doloremque. Officia sed quis voluptatem at magnam minima deleniti. Id repudiandae commodi ullam eos delectus. Excepturi consequatur tempora ducimus quia sunt praesentium. Corporis hic laboriosam eos.","jcr:primaryType":"nt:unstructured","sling:resourceType":"samples/article/news","sling:resourceSuperType":"samples/article"}