{"source":"Apache Sling's fake-content-generator","section":"Travel","folder":"travel","filename":"wyatt-reichel-on-the-panel-of-mobile-molestiae-sit-aka-sql","title":"Travel - Wyatt Reichel on the panel of mobile 'molestiae sit' (aka SQL)","tags":["protocol","array","driver"],"seeAlso":["fermin-bernhard-on-the-capacitor-of-mobile-rerum-aliquid-aka-adp","tracy-kling-on-the-sensor-of-mobile-ad-eaque-aka-sms"],"text":"As Wyatt Reichel often says, Iure ea dolorem dolores. Esse vero officiis quos sed eaque ea maiores asperiores vero. Sit et sit et eum cum vitae ducimus voluptas. Et est dignissimos numquam reprehenderit velit aut in ex maxime. Et est et. Alias suscipit enim.","jcr:primaryType":"nt:unstructured","sling:resourceType":"samples/article/travel","sling:resourceSuperType":"samples/article"}