{"source":"Apache Sling's fake-content-generator","section":"News","folder":"news","filename":"randy-jakubowski-on-the-driver-of-redundant-omnis-laborum-aka-thx","title":"News - Randy Jakubowski on the driver of redundant 'omnis laborum' (aka THX)","tags":["array"],"seeAlso":["fermin-bernhard-on-the-capacitor-of-mobile-rerum-aliquid-aka-adp","belle-jacobi-on-the-feed-of-online-vel-aut-aka-ai","tracy-kling-on-the-sensor-of-mobile-ad-eaque-aka-sms"],"text":"As Randy Jakubowski often says, Ea alias unde autem quam sunt id sit. Nesciunt rerum consequatur est. Dolorem veniam fugit et quia maiores. Eligendi et voluptas error dolor consectetur ipsa accusamus eaque. Eum sit inventore voluptate aut aliquam minus.<br/>\nTenetur ipsum optio et. Ea placeat excepturi. In quidem fugiat corporis quasi explicabo vitae. Explicabo totam minima quia nemo delectus accusamus reprehenderit optio dolor.","jcr:primaryType":"nt:unstructured","sling:resourceType":"samples/article/news","sling:resourceSuperType":"samples/article"}