{"source":"Apache Sling's fake-content-generator","section":"Music","folder":"music","filename":"greyson-vandervort-on-the-protocol-of-auxiliary-odit-aut-aka-tcp","title":"Music - Greyson Vandervort on the protocol of auxiliary 'odit aut' (aka TCP)","tags":["protocol","driver"],"seeAlso":[],"text":"As Greyson Vandervort often says, Sunt quasi sit quia nam tempore et quidem adipisci est. Fugiat inventore cum quasi ea a possimus consequatur. Quasi fugit perspiciatis nulla enim vero. Nam consequatur mollitia sit veritatis dolorem dicta in illum. Dolorem veritatis debitis tempora aut fuga est porro laudantium.<br/>\nOfficiis ut sit. Qui facilis earum repudiandae sed ab doloremque et amet eius. Quia ipsa soluta eius quia aut veniam voluptatum voluptatem. Deserunt aut est rem rerum qui ipsam. Saepe in omnis aut.<br/>\nEt quos quo ipsa reprehenderit consequatur mollitia voluptatem debitis. Quam ipsa non sed exercitationem. Repellat sed quam aliquam voluptas. In corporis nostrum.<br/>\nAutem saepe impedit ut laborum ut dolorum error excepturi. Corporis quia voluptates unde. Vitae odit magni eveniet adipisci necessitatibus quia rerum.<br/>\nLaboriosam et quam voluptatem non. Consequatur est laborum mollitia quisquam molestiae. Voluptates porro et iste quia qui deserunt. Enim sed explicabo.<br/>\nEt accusantium totam repellendus et alias quo nesciunt corporis. Omnis fugiat sequi accusamus fugiat ipsa ullam mollitia. Nobis consequuntur quod voluptatem mollitia. Consequatur aliquam qui molestiae molestiae occaecati dignissimos omnis quod qui. Tenetur ab odit odit culpa.<br/>\nTempore quos ullam totam inventore. Laboriosam qui veritatis sit ex et. Voluptatum rem dolores. Laboriosam ex est dolorem eos aut. Corporis dignissimos est eum ipsum excepturi odio eos. Optio et qui blanditiis.<br/>\nLibero adipisci consectetur voluptas inventore repudiandae perspiciatis eligendi et earum. Corporis aut voluptatem pariatur nostrum nihil. Maiores et vero suscipit minus eum veritatis architecto reiciendis. Expedita optio dolor qui iste beatae voluptas qui voluptatum accusantium. Eveniet iste sit fugit quo similique et necessitatibus.<br/>\nRerum excepturi est sapiente ullam. Sed rem reiciendis natus quia id praesentium voluptatum quam pariatur. Amet sed quis animi soluta est non et delectus. Ut nihil consequatur facilis aliquam laboriosam illo. Sapiente molestias impedit.","jcr:primaryType":"nt:unstructured","sling:resourceType":"samples/article/music","sling:resourceSuperType":"samples/article"}